{
    "variable": [
        {
            "id": "baseUrl",
            "key": "baseUrl",
            "type": "string",
            "name": "string",
            "value": "http:\/\/localhost"
        }
    ],
    "info": {
        "name": "Laravel",
        "_postman_id": "e0927394-ebc8-4f47-9691-8a79d2712a45",
        "description": "",
        "schema": "https:\/\/schema.getpostman.com\/json\/collection\/v2.1.0\/collection.json"
    },
    "item": [
        {
            "name": "Endpoints",
            "description": "",
            "item": [
                {
                    "name": "GET api\/user",
                    "request": {
                        "url": {
                            "host": "{{baseUrl}}",
                            "path": "api\/user",
                            "query": [],
                            "raw": "{{baseUrl}}\/api\/user"
                        },
                        "method": "GET",
                        "header": [
                            {
                                "key": "Content-Type",
                                "value": "application\/json"
                            },
                            {
                                "key": "Accept",
                                "value": "application\/json"
                            }
                        ],
                        "body": null,
                        "description": "",
                        "auth": {
                            "type": "noauth"
                        }
                    },
                    "response": [
                        {
                            "header": [
                                {
                                    "key": "cache-control",
                                    "value": "no-cache, private"
                                },
                                {
                                    "key": "content-type",
                                    "value": "application\/json"
                                },
                                {
                                    "key": "access-control-allow-origin",
                                    "value": "*"
                                }
                            ],
                            "code": 401,
                            "body": "{\"message\":\"Unauthenticated.\"}",
                            "name": ""
                        }
                    ]
                },
                {
                    "name": "Get a JWT via given credentials.",
                    "request": {
                        "url": {
                            "host": "{{baseUrl}}",
                            "path": "api\/login",
                            "query": [],
                            "raw": "{{baseUrl}}\/api\/login"
                        },
                        "method": "POST",
                        "header": [
                            {
                                "key": "Content-Type",
                                "value": "application\/json"
                            },
                            {
                                "key": "Accept",
                                "value": "application\/json"
                            }
                        ],
                        "body": {
                            "mode": "raw",
                            "raw": "{\"email\":\"hudson.shemar@example.com\",\"password\":\"r@P%-U~Y<>gYRfKR57\\\/^\"}"
                        },
                        "description": "",
                        "auth": {
                            "type": "noauth"
                        }
                    },
                    "response": []
                },
                {
                    "name": "Register a User.",
                    "request": {
                        "url": {
                            "host": "{{baseUrl}}",
                            "path": "api\/register",
                            "query": [],
                            "raw": "{{baseUrl}}\/api\/register"
                        },
                        "method": "POST",
                        "header": [
                            {
                                "key": "Content-Type",
                                "value": "application\/json"
                            },
                            {
                                "key": "Accept",
                                "value": "application\/json"
                            }
                        ],
                        "body": {
                            "mode": "raw",
                            "raw": "{\"name\":\"hpa\",\"email\":\"delphine30@example.net\",\"password\":\".I<)Pv:\\\"d?XAv\"}"
                        },
                        "description": "",
                        "auth": {
                            "type": "noauth"
                        }
                    },
                    "response": []
                },
                {
                    "name": "Log the user out (Invalidate the token).",
                    "request": {
                        "url": {
                            "host": "{{baseUrl}}",
                            "path": "api\/logout",
                            "query": [],
                            "raw": "{{baseUrl}}\/api\/logout"
                        },
                        "method": "POST",
                        "header": [
                            {
                                "key": "Content-Type",
                                "value": "application\/json"
                            },
                            {
                                "key": "Accept",
                                "value": "application\/json"
                            }
                        ],
                        "body": null,
                        "description": "",
                        "auth": {
                            "type": "noauth"
                        }
                    },
                    "response": []
                },
                {
                    "name": "Refresh a token.",
                    "request": {
                        "url": {
                            "host": "{{baseUrl}}",
                            "path": "api\/refresh",
                            "query": [],
                            "raw": "{{baseUrl}}\/api\/refresh"
                        },
                        "method": "POST",
                        "header": [
                            {
                                "key": "Content-Type",
                                "value": "application\/json"
                            },
                            {
                                "key": "Accept",
                                "value": "application\/json"
                            }
                        ],
                        "body": null,
                        "description": "",
                        "auth": {
                            "type": "noauth"
                        }
                    },
                    "response": []
                },
                {
                    "name": "Get the authenticated User.",
                    "request": {
                        "url": {
                            "host": "{{baseUrl}}",
                            "path": "api\/user-profile",
                            "query": [],
                            "raw": "{{baseUrl}}\/api\/user-profile"
                        },
                        "method": "GET",
                        "header": [
                            {
                                "key": "Content-Type",
                                "value": "application\/json"
                            },
                            {
                                "key": "Accept",
                                "value": "application\/json"
                            }
                        ],
                        "body": null,
                        "description": "",
                        "auth": {
                            "type": "noauth"
                        }
                    },
                    "response": [
                        {
                            "header": [
                                {
                                    "key": "cache-control",
                                    "value": "no-cache, private"
                                },
                                {
                                    "key": "content-type",
                                    "value": "application\/json"
                                },
                                {
                                    "key": "access-control-allow-origin",
                                    "value": "*"
                                }
                            ],
                            "code": 401,
                            "body": "{\"message\":\"Unauthenticated.\"}",
                            "name": ""
                        }
                    ]
                },
                {
                    "name": "Handle the incoming request.",
                    "request": {
                        "url": {
                            "host": "{{baseUrl}}",
                            "path": "api\/articles",
                            "query": [],
                            "raw": "{{baseUrl}}\/api\/articles"
                        },
                        "method": "GET",
                        "header": [
                            {
                                "key": "Content-Type",
                                "value": "application\/json"
                            },
                            {
                                "key": "Accept",
                                "value": "application\/json"
                            }
                        ],
                        "body": null,
                        "description": "",
                        "auth": {
                            "type": "noauth"
                        }
                    },
                    "response": [
                        {
                            "header": [
                                {
                                    "key": "cache-control",
                                    "value": "no-cache, private"
                                },
                                {
                                    "key": "content-type",
                                    "value": "application\/json"
                                },
                                {
                                    "key": "x-ratelimit-limit",
                                    "value": "60"
                                },
                                {
                                    "key": "x-ratelimit-remaining",
                                    "value": "59"
                                },
                                {
                                    "key": "access-control-allow-origin",
                                    "value": "*"
                                }
                            ],
                            "code": 200,
                            "body": "{\"current_page\":1,\"data\":[{\"id\":1,\"title\":\"ar1\",\"body\":\"body\",\"user_id\":1,\"created_at\":\"2024-02-13T19:52:06.000000Z\",\"updated_at\":\"2024-02-13T19:52:06.000000Z\"},{\"id\":2,\"title\":\"ar2\",\"body\":\"ar2ar2ar2ar2ar2\",\"user_id\":1,\"created_at\":\"2024-02-13T20:15:50.000000Z\",\"updated_at\":\"2024-02-13T20:15:50.000000Z\"},{\"id\":3,\"title\":\"ar4\",\"body\":\"ar2ar2ar2ar2ar2\",\"user_id\":1,\"created_at\":\"2024-02-13T20:18:06.000000Z\",\"updated_at\":\"2024-02-13T20:18:06.000000Z\"},{\"id\":4,\"title\":\"ar4\",\"body\":\"ar2ar2ar2ar2ar2\",\"user_id\":1,\"created_at\":\"2024-02-13T20:21:03.000000Z\",\"updated_at\":\"2024-02-13T20:21:03.000000Z\"}],\"first_page_url\":\"http:\\\/\\\/localhost\\\/api\\\/articles?page=1\",\"from\":1,\"last_page\":1,\"last_page_url\":\"http:\\\/\\\/localhost\\\/api\\\/articles?page=1\",\"links\":[{\"url\":null,\"label\":\"&laquo; Previous\",\"active\":false},{\"url\":\"http:\\\/\\\/localhost\\\/api\\\/articles?page=1\",\"label\":\"1\",\"active\":true},{\"url\":null,\"label\":\"Next &raquo;\",\"active\":false}],\"next_page_url\":null,\"path\":\"http:\\\/\\\/localhost\\\/api\\\/articles\",\"per_page\":10,\"prev_page_url\":null,\"to\":4,\"total\":4}",
                            "name": ""
                        }
                    ]
                },
                {
                    "name": "POST api\/articles",
                    "request": {
                        "url": {
                            "host": "{{baseUrl}}",
                            "path": "api\/articles",
                            "query": [],
                            "raw": "{{baseUrl}}\/api\/articles"
                        },
                        "method": "POST",
                        "header": [
                            {
                                "key": "Content-Type",
                                "value": "application\/json"
                            },
                            {
                                "key": "Accept",
                                "value": "application\/json"
                            }
                        ],
                        "body": {
                            "mode": "raw",
                            "raw": "{\"title\":\"adecrfntr\",\"body\":\"aut\"}"
                        },
                        "description": "",
                        "auth": {
                            "type": "noauth"
                        }
                    },
                    "response": []
                },
                {
                    "name": "Handle the incoming request.",
                    "request": {
                        "url": {
                            "host": "{{baseUrl}}",
                            "path": "api\/articles\/:article_id",
                            "query": [],
                            "raw": "{{baseUrl}}\/api\/articles\/:article_id",
                            "variable": [
                                {
                                    "id": "article_id",
                                    "key": "article_id",
                                    "value": "1",
                                    "description": "The ID of the article."
                                }
                            ]
                        },
                        "method": "GET",
                        "header": [
                            {
                                "key": "Content-Type",
                                "value": "application\/json"
                            },
                            {
                                "key": "Accept",
                                "value": "application\/json"
                            }
                        ],
                        "body": null,
                        "description": "",
                        "auth": {
                            "type": "noauth"
                        }
                    },
                    "response": [
                        {
                            "header": [
                                {
                                    "key": "cache-control",
                                    "value": "no-cache, private"
                                },
                                {
                                    "key": "content-type",
                                    "value": "application\/json"
                                },
                                {
                                    "key": "x-ratelimit-limit",
                                    "value": "60"
                                },
                                {
                                    "key": "x-ratelimit-remaining",
                                    "value": "58"
                                },
                                {
                                    "key": "access-control-allow-origin",
                                    "value": "*"
                                }
                            ],
                            "code": 404,
                            "body": "{\"message\":\"Article not found\"}",
                            "name": ""
                        }
                    ]
                },
                {
                    "name": "Handle the incoming request.",
                    "request": {
                        "url": {
                            "host": "{{baseUrl}}",
                            "path": "api\/articles\/:article_id",
                            "query": [],
                            "raw": "{{baseUrl}}\/api\/articles\/:article_id",
                            "variable": [
                                {
                                    "id": "article_id",
                                    "key": "article_id",
                                    "value": "1",
                                    "description": "The ID of the article."
                                }
                            ]
                        },
                        "method": "PUT",
                        "header": [
                            {
                                "key": "Content-Type",
                                "value": "application\/json"
                            },
                            {
                                "key": "Accept",
                                "value": "application\/json"
                            }
                        ],
                        "body": {
                            "mode": "raw",
                            "raw": "{\"title\":\"uahcsdxs\",\"body\":\"temporibus\"}"
                        },
                        "description": "",
                        "auth": {
                            "type": "noauth"
                        }
                    },
                    "response": []
                },
                {
                    "name": "Handle the incoming request.",
                    "request": {
                        "url": {
                            "host": "{{baseUrl}}",
                            "path": "api\/articles\/:article_id",
                            "query": [],
                            "raw": "{{baseUrl}}\/api\/articles\/:article_id",
                            "variable": [
                                {
                                    "id": "article_id",
                                    "key": "article_id",
                                    "value": "1",
                                    "description": "The ID of the article."
                                }
                            ]
                        },
                        "method": "DELETE",
                        "header": [
                            {
                                "key": "Content-Type",
                                "value": "application\/json"
                            },
                            {
                                "key": "Accept",
                                "value": "application\/json"
                            }
                        ],
                        "body": null,
                        "description": "",
                        "auth": {
                            "type": "noauth"
                        }
                    },
                    "response": []
                }
            ]
        }
    ],
    "auth": {
        "type": "noauth"
    }
}